chinese_library_classification/__init__.py
chinese_library_classification/chinese_library_classification.py
chinese_library_classification/utils.py
chinese_library_classification/data/data.json
chinese_library_classification-0.0.1.dist-info/LICENSE
chinese_library_classification-0.0.1.dist-info/METADATA
chinese_library_classification-0.0.1.dist-info/WHEEL
chinese_library_classification-0.0.1.dist-info/top_level.txt
chinese_library_classification-0.0.1.dist-info/RECORD
